{
  "3dm": {
    "redirect": "3dm-news",
    "name": "3DM",
    "type": "realtime",
    "column": "china",
    "home": "https://www.3dmgame.com",
    "color": "blue",
    "interval": 600000,
    "title": "新闻"
  },
  "3dm-news": {
    "name": "3DM",
    "type": "realtime",
    "column": "china",
    "home": "https://www.3dmgame.com",
    "color": "blue",
    "interval": 600000,
    "title": "新闻"
  },
  "3dm-metacritic": {
    "name": "3DM",
    "type": "realtime",
    "column": "china",
    "home": "https://www.3dmgame.com",
    "color": "blue",
    "interval": 600000,
    "title": "评测"
  },
  "gamesindustry": {
    "redirect": "gamesindustry-news",
    "name": "GIBiz",
    "type": "realtime",
    "column": "world",
    "home": "https://www.gamesindustry.biz",
    "color": "blue",
    "interval": 300000,
    "title": "产业新闻"
  },
  "gamesindustry-news": {
    "name": "GIBiz",
    "type": "realtime",
    "column": "world",
    "home": "https://www.gamesindustry.biz",
    "color": "blue",
    "interval": 300000,
    "title": "产业新闻"
  },
  "baidu": {
    "name": "百度热搜",
    "type": "hottest",
    "column": "china",
    "home": "https://www.baidu.com",
    "color": "blue",
    "interval": 600000
  },
  "gamebiz": {
    "redirect": "gamebiz-news",
    "name": "GameBiz",
    "type": "realtime",
    "column": "jp",
    "home": "https://gamebiz.jp/",
    "color": "blue",
    "interval": 600000,
    "title": "日本产业新闻"
  },
  "gamebiz-news": {
    "name": "GameBiz",
    "type": "realtime",
    "column": "jp",
    "home": "https://gamebiz.jp/",
    "color": "blue",
    "interval": 600000,
    "title": "日本产业新闻"
  },
  "gamedeveloper": {
    "redirect": "gamedeveloper-news",
    "name": "GameDev",
    "type": "realtime",
    "column": "world",
    "home": "https://www.gamedeveloper.com",
    "color": "blue",
    "interval": 600000,
    "title": "开发新闻"
  },
  "gamedeveloper-news": {
    "name": "GameDev",
    "type": "realtime",
    "column": "world",
    "home": "https://www.gamedeveloper.com",
    "color": "blue",
    "interval": 600000,
    "title": "开发新闻"
  },
  "thisisgame": {
    "redirect": "thisisgame-news",
    "name": "ThisIsGame",
    "type": "realtime",
    "column": "world",
    "home": "https://www.thisisgame.com",
    "color": "blue",
    "interval": 600000,
    "title": "韩国游戏新闻"
  },
  "thisisgame-news": {
    "name": "ThisIsGame",
    "type": "realtime",
    "column": "world",
    "home": "https://www.thisisgame.com",
    "color": "blue",
    "interval": 600000,
    "title": "韩国游戏新闻"
  },
  "indienova": {
    "redirect": "indienova-recent",
    "name": "IndieNova",
    "type": "realtime",
    "column": "china",
    "home": "https://indienova.com",
    "color": "violet",
    "interval": 600000,
    "title": "独立游戏"
  },
  "indienova-recent": {
    "name": "IndieNova",
    "type": "realtime",
    "column": "china",
    "home": "https://indienova.com",
    "color": "violet",
    "interval": 600000,
    "title": "独立游戏"
  },
  "indienova-development": {
    "name": "IndieNova",
    "type": "dev",
    "column": "china",
    "home": "https://indienova.com",
    "color": "violet",
    "interval": 600000,
    "title": "开发"
  },
  "famitsu_rank": {
    "title": "游戏销量榜",
    "name": "Famitsu",
    "type": "hottest",
    "column": "jp",
    "home": "https://www.famitsu.com",
    "color": "blue",
    "interval": 600000
  },
  "deconstructoroffun": {
    "name": "Deconstructor of Fun",
    "type": "dev",
    "column": "world",
    "home": "https://www.deconstructoroffun.com/blog",
    "color": "green",
    "interval": 3600000
  },
  "newzoo": {
    "title": "游戏市场数据",
    "name": "Newzoo",
    "type": "hottest",
    "column": "world",
    "home": "https://newzoo.com/resources",
    "color": "green",
    "interval": 3600000
  }
}